cxlint/.cxlintrc
cxlint/__init__.py
cxlint/common.py
cxlint/cxlint.py
cxlint/gcs_utils.py
cxlint/graph.py
cxlint/resources/__init__.py
cxlint/resources/agents.py
cxlint/resources/entity_types.py
cxlint/resources/flows.py
cxlint/resources/intents.py
cxlint/resources/pages.py
cxlint/resources/route_groups.py
cxlint/resources/routes.py
cxlint/resources/test_cases.py
cxlint/resources/types.py
cxlint/resources/webhooks.py
cxlint/rules/__init__.py
cxlint/rules/entity_types.py
cxlint/rules/flows.py
cxlint/rules/intents.py
cxlint/rules/logger.py
cxlint/rules/pages.py
cxlint/rules/response_messages.py
cxlint/rules/test_cases.py
cxlint/rules/webhooks.py
cxlint-1.0.4.dist-info/LICENSE.txt
cxlint-1.0.4.dist-info/METADATA
cxlint-1.0.4.dist-info/WHEEL
cxlint-1.0.4.dist-info/top_level.txt
cxlint-1.0.4.dist-info/RECORD
