Metadata-Version: 2.1
Name: cxlint
Version: 1.0.4
Summary: A static code analyzer that provides automated quality       control for Dialogflow CX Agents
Home-page: https://github.com/GoogleCloudPlatform/cxlint
Author: Patrick Marlow
Author-email: pmarlow@google.com
License: UNKNOWN
Keywords: dialogflow,cx,google,bot,chatbot,linter,dfcx
Platform: UNKNOWN
Classifier: Development Status :: 5 - Production/Stable
Classifier: Intended Audience :: Developers
Classifier: Topic :: Scientific/Engineering :: Artificial Intelligence
Classifier: Topic :: Communications :: Chat
Classifier: Topic :: Software Development
Classifier: Programming Language :: Python :: 3
Classifier: Programming Language :: Python :: 3.8
Classifier: Programming Language :: Python :: 3.9
Requires-Python: >=3.6, <4
License-File: LICENSE.txt
